metav/__init__.py
metav/main.py
metav/my_func.py
metav/pecorec.py
metav/secorec.py
metav-2.0.0.dist-info/licenses/LICENSE
metav-2.0.0.dist-info/METADATA
metav-2.0.0.dist-info/WHEEL
metav-2.0.0.dist-info/entry_points.txt
metav-2.0.0.dist-info/top_level.txt
metav-2.0.0.dist-info/RECORD
